
{"submatches": [{"play1a":"P10633","play2a":"P10653","txt":"1","scor1a":"2","scor2a":"3","game11a":"15","game12a":"12","game21a":"13","game22a":"15","game31a":"12","game32a":"15","game41a":"15","game42a":"11","game51a":"8","game52a":"15","mess":null,"retireda":"","woa":"","manmatcha":"","player1":{"playnum":"P10633","fname":"Nigel               ","lname":"Bevan               ","position":"                  ","teamnum":"T00129","teamname":"Llantrisant C         ","teamcode":"T00129"},"player2":{"playnum":"P10653","fname":"Gary                ","lname":"Fry                 ","position":"                  ","teamnum":"T00133","teamname":"Rhondda               ","teamcode":"T00133"}},{"play1a":"P10631","play2a":"P10654","txt":"2","scor1a":"3","scor2a":"0","game11a":"15","game12a":"8","game21a":"15","game22a":"12","game31a":"15","game32a":"8","game41a":"0","game42a":"0","game51a":"0","game52a":"0","mess":null,"retireda":"","woa":"","manmatcha":"","player1":{"playnum":"P10631","fname":"Chris               ","lname":"Jones               ","position":"                  ","teamnum":"T00129","teamname":"Llantrisant C         ","teamcode":"T00129"},"player2":{"playnum":"P10654","fname":"Phil                ","lname":"Eason               ","position":"                  ","teamnum":"T00133","teamname":"Rhondda               ","teamcode":"T00133"}},{"play1a":"P10640","play2a":"P10650","txt":"3","scor1a":"2","scor2a":"3","game11a":"6","game12a":"15","game21a":"15","game22a":"8","game31a":"15","game32a":"5","game41a":"10","game42a":"15","game51a":"10","game52a":"15","mess":null,"retireda":"","woa":"","manmatcha":"","player1":{"playnum":"P10640","fname":"Rich                ","lname":"Timms               ","position":"                  ","teamnum":"T00135","teamname":"Llantrisant D         ","teamcode":"T00135"},"player2":{"playnum":"P10650","fname":"Mike                ","lname":"Markey              ","position":"                  ","teamnum":"T00133","teamname":"Rhondda               ","teamcode":"T00133"}},{"play1a":"P10639","play2a":"P10723","txt":"4","scor1a":"0","scor2a":"3","game11a":"13","game12a":"15","game21a":"15","game22a":"17","game31a":"12","game32a":"15","game41a":"0","game42a":"0","game51a":"0","game52a":"0","mess":null,"retireda":"","woa":"","manmatcha":"","player1":{"playnum":"P10639","fname":"Lloyd               ","lname":"Newland             ","position":"                  ","teamnum":"T00135","teamname":"Llantrisant D         ","teamcode":"T00135"},"player2":{"playnum":"P10723","fname":"Andrew              ","lname":"Barratt             ","position":"                  ","teamnum":"T00133","teamname":"Rhondda               ","teamcode":"T00133"}},{"play1a":"P10749","play2a":"P10655","txt":"5","scor1a":"3","scor2a":"2","game11a":"15","game12a":"6","game21a":"12","game22a":"15","game31a":"15","game32a":"9","game41a":"13","game42a":"15","game51a":"15","game52a":"10","mess":null,"retireda":"","woa":"","manmatcha":"","player1":{"playnum":"P10749","fname":"Dan                 ","lname":"Webb                ","position":"                  ","teamnum":"T00135","teamname":"Llantrisant D         ","teamcode":"T00135"},"player2":{"playnum":"P10655","fname":"Virgil              ","lname":"Davies              ","position":"                  ","teamnum":"T00133","teamname":"Rhondda               ","teamcode":"T00133"}}]}